{
    "data": {
        "result": [
            {
                "metric": {
                    "__name__": "sent_external_packets_total",
                    "app_kubernetes_io_instance": "acme-qcc",
                    "app_kubernetes_io_managed_by": "Harri",
                    "app_kubernetes_io_name": "acme-qc-vpn-gw",
                    "app_kubernetes_io_version": "1.54.357-3",
                    "Harri_sh_chart": "acme-qc-vpn-gw-1.54.357-3",
                    "instance": "10.1.234.567:8443",
                    "job": "kubernetes-pods",
                    "kubernetes_namespace": "default",
                    "kubernetes_pod_name": "acme-qc-vpn-gw-6664ddfd5-n5zdd",
                    "pod_template_hash": "6664ddfd5"
                },
                "value": [
                    "2021-03-15T09:30:44Z",
                    "98"
                ]
            }
        ],
        "resultType": "vector"
    },
    "status": "success"
}